odoo/addons/l10n_cl_sii_reference_account/README.rst
odoo/addons/l10n_cl_sii_reference_account/__init__.py
odoo/addons/l10n_cl_sii_reference_account/__manifest__.py
odoo/addons/l10n_cl_sii_reference_account/i18n/es_CL.po
odoo/addons/l10n_cl_sii_reference_account/i18n/l10n_cl_sii_reference_account.pot
odoo/addons/l10n_cl_sii_reference_account/models/__init__.py
odoo/addons/l10n_cl_sii_reference_account/models/account_invoice.py
odoo/addons/l10n_cl_sii_reference_account/models/sii_reference.py
odoo/addons/l10n_cl_sii_reference_account/readme/CONTRIBUTORS.rst
odoo/addons/l10n_cl_sii_reference_account/readme/DESCRIPTION.rst
odoo/addons/l10n_cl_sii_reference_account/readme/USAGE.rst
odoo/addons/l10n_cl_sii_reference_account/static/description/icon.png
odoo/addons/l10n_cl_sii_reference_account/static/description/index.html
odoo/addons/l10n_cl_sii_reference_account/views/account_invoice.xml
odoo/addons/l10n_cl_sii_reference_account/views/sii_reference.xml
odoo12_addon_l10n_cl_sii_reference_account-12.0.1.1.0.dist-info/METADATA
odoo12_addon_l10n_cl_sii_reference_account-12.0.1.1.0.dist-info/WHEEL
odoo12_addon_l10n_cl_sii_reference_account-12.0.1.1.0.dist-info/top_level.txt
odoo12_addon_l10n_cl_sii_reference_account-12.0.1.1.0.dist-info/RECORD
